dawgdad/__init__.py
dawgdad/automation.py
dawgdad/control_charts.py
dawgdad/graphs.py
dawgdad/html_dd.py
dawgdad/msa.py
dawgdad/munging.py
dawgdad/process_capability.py
dawgdad/pyxl.py
dawgdad/rgx.py
dawgdad/sequel.py
dawgdad/stats.py
dawgdad/taguchi.py
dawgdad-1.0.9.dist-info/licenses/LICENSE
dawgdad-1.0.9.dist-info/WHEEL
dawgdad-1.0.9.dist-info/METADATA
dawgdad-1.0.9.dist-info/RECORD
