Metadata-Version: 2.4
Name: dawgdad
Version: 1.0.9
Summary: Tools for machine learning, automation, statistics, graphics
Author-email: Gilles Pilon <gillespilon13@gmail.com>
Classifier: Programming Language :: Python :: 3
Classifier: License :: OSI Approved :: MIT License
Classifier: Operating System :: OS Independent
License-File: LICENSE
Requires-Dist: basis_expansions
Requires-Dist: cached_property
Requires-Dist: beautifultable
Requires-Dist: scikit-learn
Requires-Dist: statsmodels
Requires-Dist: matplotlib
Requires-Dist: pyautogui
Requires-Dist: openpyxl
Requires-Dist: psycopg2
Requires-Dist: pyqrcode
Requires-Dist: tabulate
Requires-Dist: pyarrow
Requires-Dist: dirsync
Requires-Dist: shapely
Requires-Dist: psutil
Requires-Dist: pandas
Requires-Dist: numpy
Requires-Dist: pypng
Requires-Dist: scipy
Requires-Dist: sphinx ; extra == "doc"
Requires-Dist: pytest >=2.7.3 ; extra == "test"
Requires-Dist: pytest-cov ; extra == "test"
Project-URL: Source, https://github.com/gillespilon/dawgdad
Provides-Extra: doc
Provides-Extra: test
